exoedge_linuxstats/__init__.py
exoedge_linuxstats/__version__.py
exoedge_linuxstats-20.7.29.dist-info/DESCRIPTION.rst
exoedge_linuxstats-20.7.29.dist-info/LICENSE.txt
exoedge_linuxstats-20.7.29.dist-info/METADATA
exoedge_linuxstats-20.7.29.dist-info/RECORD
exoedge_linuxstats-20.7.29.dist-info/WHEEL
exoedge_linuxstats-20.7.29.dist-info/metadata.json
exoedge_linuxstats-20.7.29.dist-info/top_level.txt
