Metadata-Version: 2.0
Name: exoedge-linuxstats
Version: 20.7.29
Summary: An ExoEdge source for displaying linux hardware statistics and metrics.
Home-page: https://github.com/exosite/lib_exoedge_linux_stats_python
Author: Exosite LLC
Author-email: support@exosite.com
License: Apache 2.0
Keywords: murano exosite iot iiot client gateway linux stats exoedge
Platform: UNKNOWN
Classifier: Development Status :: 4 - Beta
Classifier: Programming Language :: Python :: 2.7
Classifier: Programming Language :: Python :: 3.4
Classifier: Programming Language :: Python :: 3.5
Classifier: Programming Language :: Python :: 3.6
Classifier: Operating System :: POSIX :: Linux
Classifier: Topic :: System :: Operating System Kernels :: Linux
Classifier: Topic :: Software Development :: Embedded Systems
Classifier: License :: OSI Approved :: Apache Software License
Requires-Dist: exoedge
Requires-Dist: ifparser
Requires-Dist: psutil
